Metadata-Version: 2.1
Name: setup-dist
Version: 2020.7.1
Summary: setup module for distributions: python -m setup_dist sdist --dist-dir=<dist_dir>
Home-page: https://github.com/andrewp-as-is/setup-dist.py
License: Unlicense
Keywords: setup dist sdist distribution
Platform: UNKNOWN
Classifier: License :: Public Domain
Classifier: Operating System :: OS Independent
Classifier: Programming Language :: Python :: 3
Classifier: Topic :: System :: Software Distribution 
